pyscinloopsr/__init__.py
pyscinloopsr/__main__.py
pyscinloopsr/before.py
pyscinloopsr/sr.py
pyscinloopsr-1.0.29.dist-info/METADATA
pyscinloopsr-1.0.29.dist-info/WHEEL
pyscinloopsr-1.0.29.dist-info/entry_points.txt
pyscinloopsr-1.0.29.dist-info/top_level.txt
pyscinloopsr-1.0.29.dist-info/RECORD
