Metadata-Version: 2.1
Name: pyscinloopsr
Version: 1.0.29
Summary: Read the latest PyScInLoopSr tutorials
Author: Djalma Pereira
Author-email: Djalma Pereira <pereirajunio@gmail.com>
Project-URL: Homepage, https://github.com/edjaper/pyscinloopsr
Project-URL: Documentation, https://edjaper.github.io/pyscinloopsr/
Keywords: sr,pysr,tutorial
Classifier: License :: OSI Approved :: MIT License
Classifier: Programming Language :: Python
Classifier: Programming Language :: Python :: 3
Requires-Python: >=3.9
Requires-Dist: pysr
Provides-Extra: dev
Requires-Dist: black ; extra == 'dev'
Requires-Dist: bumpver ; extra == 'dev'
Requires-Dist: isort ; extra == 'dev'
Requires-Dist: pip-tools ; extra == 'dev'
Requires-Dist: pytest ; extra == 'dev'
